{
  "2026-03-29": {
    "week": "周日",
    "articles": [
      {
        "category": "人工智能",
        "tag": "人工智能",
        "title": "Sora关闭或成AI视频现实检验时刻",
        "link": "https://techcrunch.com/2026/03/29/soras-shutdown-could-be-a-reality-check-moment-for-ai-video/",
        "summary": "Sora可能关闭引发行业反思，探讨这是正常企业策略调整，还是AI生成视频领域将出现更广泛收缩的信号。",
        "comment": "过热后的冷静期对行业长期健康发展未必是坏事。",
        "image": "",
        "score": 99
      },
      {
        "category": "数码科技",
        "tag": "AR眼镜",
        "title": "亮亮视野推出全球首创AR+AI会议翻译系统",
        "link": "https://36kr.com/p/3743855989587971?f=rss",
        "summary": "亮亮视野联合智谱AI在中关村论坛部署AR+AI会议翻译系统，支持54种语言实时翻译，延迟小于1秒，续航8小时，旨在变革传统同传模式。",
        "comment": "AR与AI结合，为实时翻译领域带来实质性效率突破。",
        "image": "",
        "score": 97
      },
      {
        "category": "数码科技",
        "tag": "量子计算",
        "title": "幺正量子获数亿元融资，加速离子阱量子计算研发",
        "link": "https://36kr.com/p/3743360666566919?f=rss",
        "summary": "合肥幺正量子完成Pre A轮数亿元融资，由蚂蚁集团和吉利资本领投，资金将用于QCCD离子阱量子计算路线研发。",
        "comment": "资本持续押注量子计算，但商业化道路仍漫长。",
        "image": "",
        "score": 96
      },
      {
        "category": "数码科技",
        "tag": "民生经济",
        "title": "全国猪价跌破5元创新低，雀巢巧克力被盗，起诉小米企业致歉",
        "link": "https://36kr.com/p/3744669439508484?f=rss",
        "summary": "全国瘦肉型生猪交易均价跌破10元/公斤，创历史新低；雀巢12吨巧克力被盗；此前起诉小米汽车的“老头乐”企业公开致歉。",
        "comment": "民生价格波动与商业纠纷并存，反映当前经济复杂面。",
        "image": "",
        "score": 94
      },
      {
        "category": "游戏影视",
        "tag": "游戏",
        "title": "《赤色沙漠》更新后Steam同时在线人数创新高",
        "link": "https://www.ign.com/articles/crimson-desert-hits-new-steam-concurrent-player-peak-as-latest-game-changing-update-kicks-in",
        "summary": "在推出重大更新后，开放世界动作冒险游戏《赤色沙漠》于第二个周末在Steam平台创下同时在线玩家数新纪录。",
        "comment": "重大更新有效提振了游戏热度与玩家参与度。",
        "image": "https://assets-prd.ignimgs.com/2026/03/29/cd-1774821305650.jpg",
        "score": 92
      },
      {
        "category": "游戏影视",
        "tag": "迪士尼",
        "title": "巴黎迪士尼“冰雪奇缘世界”正式开放，主题乐园全球扩张",
        "link": "https://www.ign.com/articles/how-frozen-jumped-from-the-big-screen-to-disney-parks-around-the-globe-including-world-of-frozen-at-disneyland-paris-disney-adventure-world",
        "summary": "巴黎迪士尼乐园正式开放全新“冒险世界”主题园区，其中包含“冰雪奇缘世界”，这是该IP在全球迪士尼乐园的又一重要落地。",
        "comment": "迪士尼持续将热门IP转化为线下体验，巩固其主题乐园的吸引力。",
        "image": "https://assets-prd.ignimgs.com/2026/03/29/olaf-1774812630927.png",
        "score": 92
      },
      {
        "category": "游戏影视",
        "tag": "电影票房",
        "title": "《拯救计划》全球票房破3亿美元，IMAX贡献显著",
        "link": "https://www.ign.com/articles/project-hail-mary-shoots-past-300-million-at-the-global-box-office-with-imax-a-big-part-of-its-success",
        "summary": "电影《拯救计划》全球票房已突破3亿美元，其中IMAX格式放映成为吸引观众、推动票房成功的重要因素。",
        "comment": "高规格放映格式正成为大片票房的重要助推器。",
        "image": "https://assets-prd.ignimgs.com/2026/03/29/phm-1774818248169.jpg",
        "score": 91
      },
      {
        "category": "游戏影视",
        "tag": "流媒体",
        "title": "Netflix公布2026年4月新片单",
        "link": "https://www.ign.com/articles/whats-new-on-netflix-april-2026",
        "summary": "Netflix公布2026年4月新上线内容，包括《狮子》《鲨鱼》《烈火男儿》及更多《怪奇物语》剧集。",
        "comment": "片单题材多样，但缺乏爆款新作。",
        "image": "https://assets-prd.ignimgs.com/2023/02/01/netflix-password-sharing-1675259762484.png",
        "score": 91
      },
      {
        "category": "游戏影视",
        "tag": "科技促销",
        "title": "TP-Link Deco 7 Pro Wi-Fi 7网状路由器在亚马逊春季大促降价35%",
        "link": "https://www.ign.com/articles/tp-link-whole-home-mesh-system-wifi-7-router-deal-amazon-spring-sale",
        "summary": "IGN报道，TP-Link Deco 7 Pro BE10000网状系统在亚马逊春季促销中降价35%，是目前最畅销的Wi-Fi 7路由器，但优惠可能很快结束。",
        "comment": "Wi-Fi 7路由器价格下探，是升级家庭网络的好时机。",
        "image": "https://assets-prd.ignimgs.com/2026/03/28/tplinkdeco-1774738623728.jpg",
        "score": 91
      },
      {
        "category": "游戏影视",
        "tag": "数码促销",
        "title": "亚马逊春季促销：16英寸便携USB显示器降价至44美元",
        "link": "https://www.ign.com/articles/best-usb-portable-monitor-deal-amazon-spring-sale",
        "summary": "IGN报道亚马逊春季促销中，Anyuse 16英寸1080p便携USB显示器价格降至44美元，可作为笔记本电脑副屏或Switch等掌机扩展屏幕。",
        "comment": "便携显示器价格新低，移动办公与游戏玩家可关注。",
        "image": "https://assets-prd.ignimgs.com/2026/03/25/anyuse-1774456378581.jpg",
        "score": 91
      },
      {
        "category": "游戏影视",
        "tag": "电商促销",
        "title": "亚马逊春季大促热销榜：多款商品低于20美元",
        "link": "https://www.ign.com/articles/the-most-popular-deals-to-come-out-of-the-big-amazon-spring-sale",
        "summary": "IGN报道亚马逊春季大促热销商品，包括Fire TV电视棒、OBD II汽车诊断仪、三文鱼DNA精华、苹果AirPods等，多款价格低于20美元。",
        "comment": "促销信息实用，但缺乏深度分析。",
        "image": "https://assets-prd.ignimgs.com/2026/03/29/amazonspringsale11-1774802722733.jpg",
        "score": 91
      },
      {
        "category": "游戏影视",
        "tag": "乐高",
        "title": "IGN推荐复活节乐高套装作为理想礼物",
        "link": "https://www.ign.com/articles/lego-easter-basket-gift-ideas",
        "summary": "IGN在复活节前夕发文，推荐多款乐高套装作为节日礼篮的完美选择，认为其比传统礼物更具新意。",
        "comment": "节日营销内容，对乐高爱好者有参考价值。",
        "image": "https://assets-prd.ignimgs.com/2026/03/26/21365-lifestyle-build-04-en-gb-1774538703362.jpg",
        "score": 90
      },
      {
        "category": "数码科技",
        "tag": "汽车科技",
        "title": "丰田铂智7售价16.98万起，集成华为小米等技术",
        "link": "https://www.ifanr.com/1660150?utm_source=rss&utm_medium=rss&utm_campaign=",
        "summary": "丰田铂智7车型起售价16.98万元，整合了华为、Momenta、小米等多家中国科技公司的技术方案，定位为融合传统车企与科技公司优势的产品。",
        "comment": "传统车企与科技公司深度捆绑，寻求智能化突围。",
        "image": "",
        "score": 89
      },
      {
        "category": "时事热点",
        "tag": "中东局势",
        "title": "伊朗袭击海湾工业设施致多人受伤",
        "link": "https://www.bbc.com/news/articles/cp86yrq5jy7o?at_medium=RSS&at_campaign=rss",
        "summary": "伊朗对阿联酋和巴林的铝业设施发动袭击，造成多人受伤，海湾地区紧张局势持续升级。",
        "comment": "地区冲突外溢风险加剧，需警惕能源供应安全。",
        "image": "",
        "score": 87
      },
      {
        "category": "时事热点",
        "tag": "中东冲突",
        "title": "以色列空袭致三名黎巴嫩记者身亡",
        "link": "https://www.bbc.com/news/articles/cgme1j70294o?at_medium=RSS&at_campaign=rss",
        "summary": "以色列军方确认空袭导致真主党旗下媒体记者阿里·舒艾布死亡，另有两名记者在袭击中丧生。",
        "comment": "战地记者安全风险加剧，国际社会应关注媒体工作者保护。",
        "image": "",
        "score": 87
      },
      {
        "category": "时事热点",
        "tag": "国际安全",
        "title": "巴黎发生针对美国银行未遂炸弹袭击，三人被捕",
        "link": "https://www.bbc.com/news/articles/cd9v234j2v7o?at_medium=RSS&at_campaign=rss",
        "summary": "法国反恐检察官办公室已立即接管调查，三名嫌疑人在巴黎因涉嫌在美国银行外策划炸弹袭击被捕。",
        "comment": "事件凸显欧洲反恐形势依然严峻。",
        "image": "",
        "score": 87
      },
      {
        "category": "时事热点",
        "tag": "艺术品盗窃",
        "title": "意大利博物馆三分钟失窃雷诺阿等名画",
        "link": "https://www.bbc.com/news/articles/cn4vw2xmpzzo?at_medium=RSS&at_campaign=rss",
        "summary": "四名蒙面男子深夜从帕尔马博物馆盗走雷诺阿、塞尚和马蒂斯画作，警方称作案仅三分钟。",
        "comment": "艺术品安全漏洞暴露，国际追索将启动。",
        "image": "",
        "score": 87
      },
      {
        "category": "游戏影视",
        "tag": "游戏折扣",
        "title": "IGN今日最佳优惠：死亡搁浅2、Switch 2游戏等",
        "link": "https://www.ign.com/articles/best-deals-for-march-29-2026",
        "summary": "IGN汇总了今日值得关注的优惠信息，包括《死亡搁浅2》预购、Switch 2游戏折扣及《电锯人》蓝光版等商品。",
        "comment": "游戏影视促销信息汇总，适合关注折扣的玩家。",
        "image": "https://assets-prd.ignimgs.com/2025/05/08/untitled-design-1-1746712983151.png",
        "score": 86
      },
      {
        "category": "时事热点",
        "tag": "伊朗冲突",
        "title": "BBC分析：特朗普对伊朗冲突的直觉决策未见成效",
        "link": "https://www.bbc.com/news/articles/c5y969pnxgvo?at_medium=RSS&at_campaign=rss",
        "summary": "BBC国际编辑撰文指出，伊朗冲突爆发一个月以来，特朗普依赖直觉的决策方式并未取得预期效果。",
        "comment": "直觉决策在复杂国际冲突中显得力不从心。",
        "image": "",
        "score": 86
      },
      {
        "category": "时事热点",
        "tag": "市场监管",
        "title": "意大利调查丝芙兰与贝玲妃向儿童营销护肤品",
        "link": "https://www.bbc.com/news/articles/c3dlk93m7jyo?at_medium=RSS&at_campaign=rss",
        "summary": "意大利竞争管理局称奢侈品巨头LVMH旗下品牌涉嫌采用“特别隐蔽”的营销策略，向儿童推广护肤品，已启动调查。",
        "comment": "监管机构正关注针对未成年人的隐蔽营销行为。",
        "image": "",
        "score": 86
      },
      {
        "category": "时事热点",
        "tag": "非洲足球",
        "title": "非洲足协秘书长因摩洛哥-塞内加尔决赛争议辞职",
        "link": "https://www.bbc.com/news/articles/cx2w8d1q70vo?at_medium=RSS&at_campaign=rss",
        "summary": "非洲足协秘书长韦龙·莫森戈-翁巴在非洲足球动荡时期辞职，此前因摩洛哥与塞内加尔决赛安排引发争议。",
        "comment": "非洲足球管理再陷危机，改革压力持续增大。",
        "image": "",
        "score": 84
      },
      {
        "category": "时事热点",
        "tag": "加拿大政治",
        "title": "加拿大新民主党选举艾维·刘易斯为新党魁",
        "link": "https://www.bbc.com/news/articles/czd74q2nqp0o?at_medium=RSS&at_campaign=rss",
        "summary": "艾维·刘易斯当选加拿大新民主党党魁，其竞选纲领聚焦于重振该左翼政党并优先保障工人权益。",
        "comment": "左翼政党试图通过新领导层重振旗鼓。",
        "image": "",
        "score": 83
      }
    ]
  }
}