{
  "2026-04-19": {
    "week": "周日",
    "articles": [
      {
        "category": "数码科技",
        "tag": "人形机器人",
        "title": "荣耀机器人“闪电”获2026亦庄人形机器人半马冠军",
        "link": "https://36kr.com/p/3773492357169920?f=rss",
        "summary": "荣耀齐天大圣队机器人“闪电”以50分26秒净用时，在21公里复杂赛道的人形机器人半程马拉松中夺冠，展示其运动稳定性与续航能力。",
        "comment": "人形机器人长距离运动稳定性取得实质性突破。",
        "image": "",
        "score": 96
      },
      {
        "category": "数码科技",
        "tag": "半导体",
        "title": "环晶芯科技获数千万元天使轮融资，实现临时键合载板循环利用",
        "link": "https://36kr.com/p/3773090942321155?f=rss",
        "summary": "环晶芯科技完成数千万元天使轮融资，资金将用于无锡量产线建设。该公司由前华为工程师创立，提供临时键合载板无损回收方案，已获龙头客户验证。",
        "comment": "硬科技创业获资本青睐，有望解决半导体制造中的材料循环难题。",
        "image": "",
        "score": 96
      },
      {
        "category": "游戏影视",
        "tag": "动画",
        "title": "《无敌少侠》第四季动画错误引发粉丝热议",
        "link": "https://www.ign.com/articles/invincible-season-4-animation-error-sparks-debate-amongst-fans",
        "summary": "亚马逊Prime Video动画《无敌少侠》第四季出现角色形象绘制错误，导致主角马克·格雷森外观异常，引发粉丝对动画制作质量的讨论。",
        "comment": "制作瑕疵引发讨论，反映观众对细节的关注度。",
        "image": "https://assets-prd.ignimgs.com/2026/04/01/invincible-s4-ep5-thumb-1775063995047.jpg",
        "score": 91
      },
      {
        "category": "数码科技",
        "tag": "机器人",
        "title": "2026机器人半马垫底，萌翻全场",
        "link": "https://www.ifanr.com/1662773?utm_source=rss&utm_medium=rss&utm_campaign=",
        "summary": "2026年机器人半程马拉松比赛中，出现史上最萌垫底机器人，引发关注。",
        "comment": "娱乐性大于竞技性，展现机器人设计的趣味一面。",
        "image": "",
        "score": 88
      },
      {
        "category": "游戏影视",
        "tag": "游戏评测",
        "title": "《识质存在》游戏体验速报：六年等待后的初评",
        "link": "https://www.gcores.com/radios/213473",
        "summary": "历经六年跳票，《识质存在》正式发售。本期速报基于两天深度体验，探讨其战斗与黑客并行的玩法、流程长度争议及多周目内容。",
        "comment": "玩法新颖，但流程长度可能引发争议。",
        "image": "",
        "score": 88
      },
      {
        "category": "时事热点",
        "tag": "战争罪",
        "title": "澳大利亚最高荣誉士兵被控战争罪，誓言抗争",
        "link": "https://www.bbc.com/news/articles/cy91r7ww3weo?at_medium=RSS&at_campaign=rss",
        "summary": "澳大利亚功勋士兵本·罗伯茨-史密斯被控五项谋杀战争罪，首次公开声明将坚决抗辩。",
        "comment": "案件将考验澳大利亚对战争罪行的追责决心。",
        "image": "",
        "score": 87
      },
      {
        "category": "时事热点",
        "tag": "俄乌冲突",
        "title": "泽连斯基谴责美国延长对俄制裁豁免",
        "link": "https://www.bbc.com/news/articles/c248m3z49j1o?at_medium=RSS&at_campaign=rss",
        "summary": "美国延长对俄罗斯部分能源交易的制裁豁免，称旨在缓解因美以与伊朗冲突引发的能源供应紧张。乌克兰总统泽连斯基对此表示谴责。",
        "comment": "美国在能源安全与对俄施压间面临两难。",
        "image": "",
        "score": 87
      },
      {
        "category": "时事热点",
        "tag": "社会事件",
        "title": "特立尼达墓地发现50具婴儿遗体被弃",
        "link": "https://www.bbc.com/news/articles/ce8jl1271pjo?at_medium=RSS&at_campaign=rss",
        "summary": "警方初步调查显示，这可能是“非法处理无人认领尸体”的案件，目前正在调查遗体来源和处理方式。",
        "comment": "事件性质恶劣，暴露殡葬管理严重漏洞。",
        "image": "",
        "score": 87
      },
      {
        "category": "时事热点",
        "tag": "中东局势",
        "title": "法国维和人员在黎巴嫩南部遇袭身亡",
        "link": "https://www.bbc.com/news/articles/cvg4mrm2vm0o?at_medium=RSS&at_campaign=rss",
        "summary": "法国总统马克龙指责真主党发动袭击，伊朗支持的武装组织否认与事件有任何关联。",
        "comment": "中东局势因维和人员遇袭再度紧张。",
        "image": "",
        "score": 87
      },
      {
        "category": "时事热点",
        "tag": "国际关系",
        "title": "教皇澄清“暴君”言论并非针对特朗普",
        "link": "https://www.bbc.com/news/articles/ce84j261kj1o?at_medium=RSS&at_campaign=rss",
        "summary": "教皇方济各表示其关于“暴君”的言论被误解，此前该言论引发与美国总统的争执。",
        "comment": "宗教领袖言论再陷外交风波，折射国际关系敏感度。",
        "image": "",
        "score": 86
      }
    ]
  }
}